{
  "block_size": 512,
  "batch_size": 24,
  "grad_accum": 3,
  "num_epochs": 1,
  "vocab_size": 16384,
  "dataset_split": "train",
  "learning_rate": 5e-05,
  "weight_decay": 0.05,
  "head_weight_decay": 0.005,
  "warmup_steps_proportion": 0.1,
  "checkpoint_path": "model_babylm_bert_ltg_checkpoint_debug",
  "cache_path": "./model_babylm_bert_ltg_sentence_aware_debug",
  "chunk_size": 40,
  "tokenizer_path": "./data/pretrain/wordpiece_vocab.json",
  "hidden_size": 768,
  "intermediate_size": 2048,
  "num_attention_heads": 12,
  "num_hidden_layers": 2,
  "max_position_embeddings": 512,
  "use_sentence_aware": true,
  "doc_max_lines": 10000,
  "debug_max_raw_lines": 40000
}